[
    {
        "object_name": "cup", 
        "measurements": [
            {
                "name": "friction", 
                "value": "0.4"
            }, 
            {
                "name": "weight", 
                "value": "4"
            }
        ], 
        "object_id": "1"
    }, 
    {
        "object_name": "box", 
        "measurements": [
            {
                "name": "friction", 
                "value": "0.3"
            }, 
            {
                "name": "weight", 
                "value": "2"
            }, 
            {
                "name": "density", 
                "value": "0.3"
            }
        ], 
        "object_id": "2"
    }
]